<?xml version='1.0' encoding='utf-8' standalone='yes' ?>
<Items>
<Timeline path="/Sounds/Sprachmemo*.m4a" type="raw">
        <python run="android_filename.py">
            <type text="Voicenote (German)" category="Media"/>
            <filename>
                <field addfields="{%1}"/>
            </filename>
            <package/>
            <timestamp field="{%0}" int="/1000"/>
            <duration/>
            <desc/>
            <contact/>
            <contact_alias/>
            <message/>
        </python>
</Timeline>
<Timeline path="/Sounds/Voicenote*.m4a" type="raw">
        <python run="android_filename.py">
            <type text="Voicenote" category="Media"/>
            <filename>
                <field addfields="{%1}"/>
            </filename>
            <package/>
            <timestamp field="{%0}" int="/1000"/>
            <duration/>
            <desc/>
            <contact/>
            <contact_alias/>
            <message/>
        </python>
</Timeline>
</Items>